mavats/MAR.py
mavats/__init__.py
mavats/alphaPCA.py
mavats/factormodel.py
mavats-0.1.5.dist-info/LICENSE
mavats-0.1.5.dist-info/METADATA
mavats-0.1.5.dist-info/WHEEL
mavats-0.1.5.dist-info/RECORD
